[
  {
    "image": "IMG_20241118_100033_anonimized.jpg",
    "caption": "a picture of a car with a license plate number",
    "ocr": "i\n\nZ:(VINYZSOQW) WP\u00a5LWd OLIVADISSIGIS\nTZOZAIISVLUYAD\n\n \n\n} HOP Ositgag\n\nMONG INTVONOT\n\nJDVZSYOUVADVIA"
  },
  {
    "image": "IMG_20241118_100037_anonimized.jpg",
    "caption": "a picture of a car with a license plate number",
    "ocr": "\u2019 f\n\na\npe\no\nSS |\n\u2122\no\nio"
  },
  {
    "image": "IMG_20241118_100047_anonimized.jpg",
    "caption": "a photo of a car with a license plate number on it",
    "ocr": "MAGYARORSZAG\n\nFORGALMI ENGE! ELY\n\nPREMike Heeire\n\nde\n\n \n\nDez ~O5.i1.\nOH\n\n(3)\n\nGYARTAS! \u00a3V2021\nSEBESSEGVALTO FAJTAJA (KODSZAMA):2\n\n\u2018 SS RRR\nRes"
  },
  {
    "image": "IMG_20241118_100056_anonimized.jpg",
    "caption": "a picture of a car with a license plate number and a number of cars in the background",
    "ocr": "wiiutiths weere 2022 MA} 12\n\niene ora\n\n  \n  \n \n\n \n  \n\ny Bo. } Vali, te De\n\nxvaltua . 2024 OKF 8S C\n\n   \n              \n\nCa\n\n  \n\n2: legnagyobb ieadott ~~\n\n     \n   \n \n\nE: \u2014_ alvazszam P.\n\nF.1: egyittes timeg teljesitm\u00e9nye (KW)\nG:  sajat tomeg (ha rendelkez\u00e9sre all)\n\nH: \u2014 okm\u00e9ny \u00e9rv\u00e9nyess\u00e9g\u00e9nek -P.3:hajtanyaga\n\n    \n\nideje (ha nem korlatlan) P.5:  motork\u00e9d /szam\nI: els magyarorszagi nyilvan- \u00a9 Q: \u2014 teljesitm\u00e9ny/tomeg arany\ntartasba v\u00e9tel id6pontja (KWAKg) \\\nJ: jar kateg\u00e9ridja sak m okra),\nK: __ tipus-jGvahagyasi szam (ha van)\n0: \u2014 vontatasi adatok (kg)\n0.1: f\u00e9kezett\n0.2: f\u00e9kezetlen\n(0): 16k niki\n(1): rafut\u00e9f\u00e9kkel\n(2): atmendfekke!\n(3): nyeregterhel\u00e9s\nP.1: hengertirtartalma (cm*)\n\n   \n \n\n  \n  \n\n    \n \n\n    \n\n    \n   \n \n    \n   \n   \n   \n    \n\nMONA\n~\u2014\n\n\\"
  },
  {
    "image": "IMG_20241118_100943_anonimized.jpg",
    "caption": "a car is parked on a gravel road",
    "ocr": "|\n\u2014\u2014 ol\n\nere acy\n\nbi\n\n \n\n \n\n \n\nloner\n\nae\nbees Peg faaet| E"
  },
  {
    "image": "IMG_20241118_100949_anonimized.jpg",
    "caption": "a car is parked on a gravel driveway",
    "ocr": ""
  },
  {
    "image": "IMG_20241118_100958_anonimized.jpg",
    "caption": "a car is parked on a gravel driveway",
    "ocr": ""
  },
  {
    "image": "IMG_20241118_101004_anonimized.jpg",
    "caption": "a photo of a car with a license plate on it",
    "ocr": "7 pany names pate ee bald a A\nATM ALT Oe\nCU ULM M TE \u00a33\n\n= b i. iF"
  },
  {
    "image": "IMG_20241118_101008_anonimized.jpg",
    "caption": "a car is parked on a gravel lot",
    "ocr": "Ce Arauh,\nSeve {4s\n\nf 4\na \u00bbe\nig\nara\n\nade ad, A FT\n\nAEE i\n\nWi\nVI ay\n\nVas\n\nAi\n\n/\n\nde TT EF\nLL ATT ys,\n\niy\nTAL:\nMULL\n\nLLL\n\n(a\n\nSy rs\n=\n\nYH > 0 fas\nSS te XN\nTat \u00b0 hy\" a SROTY\n\nRRR SS\n\nSRI NSN\nBS\ny\n\nma AE i ROS NTS x AS NSS\nNeat ? ~\n7 \u201c es i Y 2 WAS\n\nSy\nie\n\nSS"
  },
  {
    "image": "IMG_20241118_101105_anonimized.jpg",
    "caption": "a car dashboard with a number of numbers on it",
    "ocr": ""
  },
  {
    "image": "IMG_20241118_101114_anonimized.jpg",
    "caption": "a photo of a car with a license plate number",
    "ocr": ""
  },
  {
    "image": "IMG_20241118_101119_anonimized.jpg",
    "caption": "a close up image of a car with a license plate",
    "ocr": "Praha"
  },
  {
    "image": "IMG_20241118_101128_anonimized.jpg",
    "caption": "a photo of a car with a license plate number",
    "ocr": ""
  },
  {
    "image": "IMG_20241118_101131_anonimized.jpg",
    "caption": "a car is shown with a license plate number ls",
    "ocr": "Hl\n\nseamen on 8 eet\n\nTa"
  },
  {
    "image": "IMG_20241118_101134_anonimized.jpg",
    "caption": "a car dashboard with a chevrolet logo",
    "ocr": "Ih\n\nID\n\nUl]\n\nIH\n\n\u00bb\n\na)\n\nI\n\nBu\n\n2024-11-18\n\naie eet\n\nm3\n\nznald kiv\u00e9laszt | Foly =\n\n      \n\nSn"
  },
  {
    "image": "IMG_20241118_101137_anonimized.jpg",
    "caption": "a photo of a guitar with a white background",
    "ocr": "BLN\n\naio"
  },
  {
    "image": "IMG_20241118_101153_anonimized.jpg",
    "caption": "a car is shown with a dashboard and a steering wheel",
    "ocr": "Weyer,\n5 Sibek Reka ba\n\nAe\nPea e\n\nWea aaiars\n\n\"i we e RASS:\n\nPy\nUU"
  },
  {
    "image": "IMG_20241118_101207_anonimized.jpg",
    "caption": "a close up of a tv screen with a number of numbers on it",
    "ocr": "g\n\n4200 kg\n\nLl= 1160 kg\n'2- 1135 kg\n\nDE-85045 Ingolstadt\nGermany"
  },
  {
    "image": "IMG_20241118_101220_anonimized.jpg",
    "caption": "a car is shown with a license plate number and a license plate number",
    "ocr": "a ae\n\neat\nwe"
  },
  {
    "image": "IMG_20241118_101223_anonimized.jpg",
    "caption": "a picture of a car with a license plate number",
    "ocr": ""
  },
  {
    "image": "IMG_20241118_101227_anonimized.jpg",
    "caption": "a picture of a car with a license plate number ls",
    "ocr": "ct \u2014 ats \u2014 = \u2014 i ea pat _\u2014 tae wi\n\u2014 \u2014~ \u2014v a \u2014 ra ee es 2 <\n\u2014 = \u2014 a8 \u2014 = 3\n\u2014 _\u2014 - 5\n\n \n\naf EES\non"
  },
  {
    "image": "IMG_20241118_101231_anonimized.jpg",
    "caption": "a white background with a circular pattern",
    "ocr": "Xt\nXS\n\nYS\nEAN\n\nRE\n\nnS\nRR\n\nNy RE\n\u2018 x\ni A ENN"
  },
  {
    "image": "IMG_20241118_101308_anonimized.jpg",
    "caption": "a dashboard with a number of gauges and a clock",
    "ocr": "N. dsszek\u00e9tve\n\n__ eee"
  },
  {
    "image": "IMG_20241118_101313_anonimized.jpg",
    "caption": "a car dashboard with a red light on it",
    "ocr": "a\n\nH\u00e9tf6\n\nREADY 2024-11-18 ar ee\n\npapal 25617 km Va ACY"
  },
  {
    "image": "IMG_20241118_101318_anonimized.jpg",
    "caption": "a car dashboard with a number of buttons and a red arrow",
    "ocr": "han \u00a3 N, \u00e9sszek\u00e9tve Y\n\n  \n   \n  \n   \n \n\nzar\u00e96gombot az el\u00e9v.\n\n \n\nalloaead karon megnyomni\naie I-50 ee LEAL\n\n14:11 Te\n\nSIO ea a"
  },
  {
    "image": "IMG_20241118_101324_anonimized.jpg",
    "caption": "a close up of a computer screen with a blue screen",
    "ocr": "Ses\nSees\n\na SSS"
  },
  {
    "image": "IMG_20241118_101332_anonimized.jpg",
    "caption": "a blurry image of a car with a license plate on it",
    "ocr": "4\n\naoe ba Mestre coin)\n\n\u2018S)\nMenetfok.\nLey) Jefe Loy 4\nLs) dete Fl altel B\nzar\u00e9gombot az el\u00e9v.\nkaron megnyomni\n\nthd ny 0 ACT\nae 8 # +45\n\n<2"
  },
  {
    "image": "IMG_20241118_101342_anonimized.jpg",
    "caption": "a dashboard of a car with a steering wheel and buttons",
    "ocr": ""
  },
  {
    "image": "IMG_20241118_101345_anonimized.jpg",
    "caption": "a blurry image of a car with a license plate number",
    "ocr": "Pp pdt sper\n\nmmol eel}\n\n \n\n \n\nNEMEC a\nMegjegyz\u00e9s\n\na Ect mrt Moe Vaneiver Teac oo\nele SE ce) Co ut7 a"
  },
  {
    "image": "IMG_20241118_101348_anonimized.jpg",
    "caption": "a digital image of a car with a license plate number",
    "ocr": ""
  },
  {
    "image": "IMG_20241118_101353_anonimized.jpg",
    "caption": "a car dashboard with a chevrolet logo",
    "ocr": "AAS tk <\n\nELAM y.\n\nCyAA Pee\nyA\n\n,\n\n-\nM,"
  },
  {
    "image": "IMG_20241118_101357_anonimized.jpg",
    "caption": "a photo of a car with a license plate number ls",
    "ocr": "Wwe A Bey te\nN91 | PN Ze 7 ee Sa dca\nmith) ly AG!) 1 eee\n\nhee ie\noutage PD\n\nay yn\nne\na i hy pag\n\naa\nve i]\n\nSear Tine\n\nfy econ\n\nx\n\na"
  },
  {
    "image": "IMG_20241118_101415_anonimized.jpg",
    "caption": "a paper with a title of collateral appraisal assistant",
    "ocr": "Gyartmany, tipus:\nAUDI i :\nQ3 40 TFSI S line quattro S-tronic 25.000km! Magyarorszagi! UISZERGI\n\nEvjarat: MUuszaki vizsga \u00e9rv\u00e9n ;\n2022/5 ine\nHengerdirtartalom: nares\nae : Uzemanyag:\n\nBenzin\nTeljesitm\u00e9ny: Km. 6ra allas:\n140 kW, 190 LE 25 000 km\nKlima fajtaja: Sebess\u00e9gvalto:\n\nAutomata (7 fokozatu tiptronic) sebess\u00e9gvalt6\n\nDigitalis k\u00e9tz\u00e9nas klima\n4\n\nablak hatul - centr\u00e9izar\n\n| ABS (blokkolasgatl6) - vezet\u00e9oldali l\u00e9gzsak \u2014 utasoldali l\u00e9gzsak \u2014 oldall\u00e9gzsak \u2014 fiiggdnyl\u00e9gzsak \u2014 elektromos ablak eld! \u2014 elektrom\n| hangsz6r\u00e9 \u2014 Android Auto \u2014 Apple CarPlay \u2014 ASR (kip\u00e9rg\u00e9sgatl6) \u2014 automata (7 fokozatu tiptronic) sebess\u00e9gvalt6 \u2014 automatikusan s\u00e9t\u00e9ted6 bels\u00e9 tiik\u00e9r -\n\n| automatikusan s\u00e9t\u00e9ted6 kiils6\u00e9 tiik\u00e9r \u2014 allithato combtamasz \u2014 allithat\u00e9 kormany \u2014 bluetooth-os kihangosit\u00e9 \u2014 b\u00e9rkormany - der\u00e9ktamasz - digitalis k\u00e9tzonas klima -\n6-eloszt6) \u2014 elektromos csomagt\u00e9rajt6-mozgatas - elektromos tiik6\u00e9r - elektromosan behajthat6 kiils\u00e9 tukrok\n16 - fed\u00e9lzeti komputer \u2014 fiithet6 ablakmos6 favokak - fiithet6 els\u00e9 iil\u00e9s \u2014 fithetd\n\n| digitalis mGszeregys\u00e9g \u2014 EBD/EBV (elektronikus f\u00e9ker\n| els6-h4ts6 parkoloradar \u2014 es6szenzor \u2014 ESP (menetstabilizator) \u2014 faradtsag\u00e9rz\u00e9ke\nllen\u00e9rz6 rendszer \u2014 hats6 fejtamlak \u2014 inditasgatlo (immobiliser) - ISOFIX rendszer \u2014 kikapcsolhato\nnditas \u2014 kulcsn\u00e9lkili nyit6rendszer \u2014 multifunkci\u00e9s kormanyker\u00e9k - potker\u00e9k \u2014 savtart6 rendszer \u2014\nG \u2014 start-stop/motormegallit\u00e9 rendszer \u2014 szinezett tiveg - tavolsagi fenysz6r6 asszisztens \u2014\nforgalomba helyez\u00e9s Magyarorszagon \u2014 garantalt km\n\nfit\u00e9szalas sz\u00e9lv\u00e9d6\u00e9 \u2014 GPS (navigacid) - guminyomas-e\n30%-t\u00e9l elvihet\u00e9. Magyarorszagon vasarolt, szalon\nciaval\n\n| tukor\n| l\u00e9gzsak \u2014 kOnnyGf\u00e9m felni \u2014 k\u00e9z\u00e9ps\u00e9 kartamasz \u2014 kulcsn\u00e9lkul\n| savvalt\u00e9 asszisztens \u2014 sebess\u00e9gfiiggd szerv\u00e9kormany \u2014 sportfutom\nUSB csatlakoz6 \u2014 Ul\u00e9smagassag 4llitas. Aut\u00e9beszamitas lehets\u00e9ges \u2014 azonnal elvihet6 \u2014 els6\u00e9\n- t\u00e9rzsk\u00e9nyv \u2014 v\u00e9gig vezetett szervizkonyv \u2014\n4lland6\u00e9 \u00e9sszker\u00e9khajtassal. 4 \u00e9ves koraig (2026.05-ig) teljesk\u00e9ri gyari garan\nnnyuf\u00e9m felni,\n\n| tolatokamera\nem dohanyz6 \u2014 rendszeresen karbantartott\ner\u00e9s k\u00e9tliteres benzinmotor,\n\u00e9ssel lehets\u00e9ges.\n\nfutas keveset futott\n| Silapotu g\u00e9pkocsi, els\u00e9 hasznaldjatol! S-Line kivitel,\nrendelkezik! S\u00e9rul\u00e9smentes el\u00e9\u00e9let! Holtt\u00e9rfigyel6, savtarto, adaptiv Matrix LED f\u00e9nyszoro,\n\nombtamaszos sportil\u00e9sek. Kedvez6 lizing lehet\u00e9s\u00e9g akar 30 szaza\n\ntolatokamera \u00e9s parkol\u00e9asszisztens, 19coll S-Line ko\nl\u00e9k Gner\u00e9vel, beszamitas-csere realis \u00e9rt\u00e9kegyeztet!\n\ntavolsagtarto tempomat"
  }
]