[
  {
    "image": "IMG_20241112_133308_anonimized.jpg",
    "caption": "a photo of a car with a license plate on it",
    "ocr": "tome testa etcmettanti\n\nRS\n\nATA"
  },
  {
    "image": "IMG_20241112_133314_anonimized.jpg",
    "caption": "a red car is parked on a brick driveway",
    "ocr": ""
  },
  {
    "image": "IMG_20241112_133319_anonimized.jpg",
    "caption": "a car is parked on a driveway with a license plate on it",
    "ocr": ""
  },
  {
    "image": "IMG_20241112_133327_anonimized.jpg",
    "caption": "a car is parked on a white background",
    "ocr": ""
  },
  {
    "image": "IMG_20241112_133333_anonimized.jpg",
    "caption": "a car is parked on a gravel lot",
    "ocr": "my OS. ,\nGOR HIS +33-\nFa\n\n\u00a5"
  },
  {
    "image": "IMG_20241112_133336_anonimized.jpg",
    "caption": "a car is parked on a grassy area",
    "ocr": ""
  },
  {
    "image": "IMG_20241112_133343_anonimized.jpg",
    "caption": "a close up of a car with a license plate number",
    "ocr": "spp TMS) ee\nSS RSSTR LE a\nUS ee 7 dT\n\ni ae | es\nBeal oe\na Vota"
  },
  {
    "image": "IMG_20241112_133412_anonimized.jpg",
    "caption": "a dashboard with a speedometer and a tachometer",
    "ocr": ""
  },
  {
    "image": "IMG_20241112_133442_anonimized.jpg",
    "caption": "a photo of a car with a license plate number",
    "ocr": ""
  },
  {
    "image": "IMG_20241112_133446_anonimized.jpg",
    "caption": "a digital image of a car with a license plate number",
    "ocr": ""
  },
  {
    "image": "IMG_20241112_133448_anonimized.jpg",
    "caption": "a car is parked in a parking lot with a license plate number",
    "ocr": "pc\n\nee\n\nSCL TPC ESL LE SLIPPED I ICSC"
  },
  {
    "image": "IMG_20241112_133453_anonimized.jpg",
    "caption": "a digital image of a car with a license plate number 5",
    "ocr": "Orn Cm aaah iy >"
  },
  {
    "image": "IMG_20241112_133503_anonimized.jpg",
    "caption": "a computer screen with a yellow background and a yellow title bar",
    "ocr": "\u2018 WZ6 9100876217\nWS6 S1G08/6217\n| A26 81uZ0\u00a276r3\nAl6 LIUS%/Szz\nH16 918SS/S0z\n[ H16 Stus9/cer\u2014\n(IS0/42q)eqy :1/2y - yonup\n\n- 4 U\n\nQ)Edy \u2018ploy e [\n\nna"
  },
  {
    "image": "IMG_20241112_133511_anonimized.jpg",
    "caption": "a photo of a car with a license plate number",
    "ocr": "s ng! ee\ni? :"
  },
  {
    "image": "IMG_20241112_133524_anonimized.jpg",
    "caption": "a car with a license plate number ls",
    "ocr": ""
  },
  {
    "image": "IMG_20241112_133542_anonimized.jpg",
    "caption": "a photo of a car with a license plate number",
    "ocr": ""
  },
  {
    "image": "IMG_20241112_133545_anonimized.jpg",
    "caption": "a car with a license plate number ls",
    "ocr": ""
  },
  {
    "image": "IMG_20241112_133552_anonimized.jpg",
    "caption": "a photo of a car with a red light on it",
    "ocr": "or? WMeteyY a =\n\n   \n \n\n \n\nsata"
  },
  {
    "image": "IMG_20241112_133556_anonimized.jpg",
    "caption": "a car is shown in a blurry image with a license plate number",
    "ocr": ""
  },
  {
    "image": "IMG_20241112_133614_anonimized.jpg",
    "caption": "a photo of a car with a red and blue stripe on the side",
    "ocr": "Pare are i!\nRaat TPN AL aX\nf ~ Tae x VX op We j\n\ny\n\n7 1g\n>I . s al aa L\nvu AM Vy PME Ms\n\n. pe\n\nrc"
  },
  {
    "image": "IMG_20241112_133626_anonimized.jpg",
    "caption": "a digital image of a car with a license plate",
    "ocr": ""
  },
  {
    "image": "IMG_20241112_133629_anonimized.jpg",
    "caption": "a white image of a car with a white license plate",
    "ocr": ""
  },
  {
    "image": "IMG_20241112_133654_1_anonimized.jpg",
    "caption": "a dashboard with a red number on it",
    "ocr": ""
  },
  {
    "image": "IMG_20241112_133654_anonimized.jpg",
    "caption": "a dashboard with a speedometer and a tachometer",
    "ocr": ""
  },
  {
    "image": "IMG_20241112_133658_anonimized.jpg",
    "caption": "a dashboard with a red number on it",
    "ocr": ""
  },
  {
    "image": "IMG_20241112_133706_anonimized.jpg",
    "caption": "a dashboard with a red light on it",
    "ocr": "ge ie,\n\u00ab \u2018100 '29 140\u00b0,\n\nadn)"
  },
  {
    "image": "IMG_20241112_133712_anonimized.jpg",
    "caption": "a person is sitting in a chair with a laptop computer",
    "ocr": ""
  },
  {
    "image": "IMG_20241112_133717_anonimized.jpg",
    "caption": "a photo of a car with a red light on it",
    "ocr": ""
  },
  {
    "image": "IMG_20241112_133721_anonimized.jpg",
    "caption": "a dashboard with a chevrolet saturn saturn saturn saturn saturn saturn saturn saturn saturn saturn saturn saturn saturn saturn saturn saturn saturn saturn saturn saturn saturn saturn ",
    "ocr": "PPS Ee\naE."
  },
  {
    "image": "IMG_20241112_133723_anonimized.jpg",
    "caption": "a photo of a car with a license plate number",
    "ocr": "oy SESS\nvar\n\n; r , ne | if\ne ate KM : Neary\nSES ve Pat RUN INT CRUEL\n\n \n\n  \n\n \n\n \n \n\nSe\n\n \n\ntad"
  },
  {
    "image": "IMG_20241112_133727_anonimized.jpg",
    "caption": "a car dashboard with a clock and a clock on it",
    "ocr": "+\n\nk\n\ngalerdekcbenine scan\n\nSRR ESS\n\n\u2014\neee\n\nen\n\nON me Ge\nnae\n\nie\n\nIEEE\n\na\n\nlcd:\n\nmone\n\nara.\n\n \n\nwor\na\n\na\none\n\nCi\n4\nWig g\n\nHE;\n\nT\n\nEp pg SIMA\nSoro aie\n\ngir\n\n \n\nre\n\n \n\n \n\npee\n\nA"
  },
  {
    "image": "IMG_20241112_133759_anonimized.jpg",
    "caption": "a person is holding a paper with a title of collateral appraisal assistant",
    "ocr": ""
  },
  {
    "image": "IMG_20241112_133900_anonimized.jpg",
    "caption": "a black and white image of a car with a red and black chevron logo",
    "ocr": ""
  },
  {
    "image": "IMG_20241112_133921_anonimized.jpg",
    "caption": "a car is parked on a white background with a number of screws on it",
    "ocr": "LON oP a \u00bb\nSob ime eS * a\n- mtd\nee ee\n\nce nate"
  },
  {
    "image": "IMG_20241112_133932_anonimized.jpg",
    "caption": "a picture of a car with a license plate number on it",
    "ocr": "MAGYARORSZAG\n| FORGALMI ENGEDELY\n\nTi 2018.01.30.\nUE\n(OO)\n(2)\n()\nGYARTASI EV: 2018\n\nSEBESSEGVALTO FAJTAJA (KODSZAI\ni )\n\nal\n\n \n\nEUROPAI KOZOSSEG\n\nmiaty tus+Premetna \u00a2\n\nH"
  },
  {
    "image": "IMG_20241112_133937_anonimized.jpg",
    "caption": "a document with a title of collateral appraisal assistant",
    "ocr": "Zo hA. fe.\n\nKodmagyarazat:\n\nele)\n\n \n\nC.1 forgalmi engedely jogosult}\n\nC.1.1: csaladi n\u00e9v vagy cf\n0.1.2 f\n\n0.1.3\nC.4 6, hogy a\n\njOgosit\n\nD.1\nD.2\nD.3\n\n* wu srs\n(G2 ddl\nYuGe k4t 4 %\nAb Vo tote [Shes\n\nalyazszam\n\n; egyuttes tomeg\n\nSajal tomeg\n\n  \n\nokmany \u00e9rvenyessegenek\nideje (t nk\nnag 4 $Zag\nDa velel id\njarmu Kategoridja\ntipus-jovahagy\ntatasi adatok (kg\n\ney os\n\" ct\n\n \n\nOnos - armikereske Sd\u00e9\n\nSebessegvalto fajtaja"
  },
  {
    "image": "IMG_20241112_133953_anonimized.jpg",
    "caption": "a document with the title collateral appraisal assistant",
    "ocr": "- Fontos figyelmeztetes\n\nKerjuk, tartsa ezt a k\u00e9zikonyvet KIA jarmiiv\u00e9ben.\n\u00e9gess\u00e9ge eset\u00e9n at kell adni\n\nEzt a k\u00e9zikonyvet garancialis javitas sziiks\naklAmai i _Ezta k\u00e9zikonyvet a jarmG\u00e9 eladasakor at kell adni\n\naz Uj tulajdonosnak, hogy a k\u00e9vetkez6 tulajdonosok is rendelkezzenek a\nbenne foglalt informacidkkal.\n\nMeghatarozasok Cs. KIA Modell\nAszerint, ahogy \u20ac k\u00e9zikonyvben hasznaljuk (kiveve, ha specialis esetben Cee! a\nmast allitunk): \u2014 y\n\n\u201cKIA\u201d jelent\u00e9se: Kia Motors \u20acS leanyvallalatai.\n\nA leanyvallalat barmely olyan vallalat, amely felett k\u00e9zvetlen vagy k6z-\nvetett modon mas term\u00e9szetes vagy jogi szem\u00e9ly iranyito befolyast gya-\nkorol, illetve ezen mas term\u00e9szetes vagy jogi szem\u00e9ly mas term\u00e9szetes eke?\n\nvagy jogi szem\u00e9lyekkel kOzosen gyakorol iranyito befolyast. zs\n\nA KIA megk\u00e9t\u00e9sek n\u00e9lkul leanyvallalatnak tekinti a KIA Motors Europe Keresked6 neve\nGmbh-t (KME) \u00e9s KIA Motors Slovakia s.r.o.-t (KMS).\n\namco Tower 679-4 Yeoksam- Keresked6 telefons.\na tartal\u00e9k alkatr\u00e9szek es tarto- KIA MOTOR\n\n25.\n\nJarmt\u00e9 adatai\n\n \n  \n   \n    \n   \n   \n  \n   \n  \n \n \n  \n  \n    \n  \n    \n  \n \n \n \n \n\n \n \n \n \n \n \n \n \n \n   \n   \n   \n    \n    \n \n   \n      \n\n\u201cMobis\u201d jelent\u00e9se: Hyundai Mobis, Rod\ndong, Gangnam-gu, Seoul, Korea, amely\nz\u00e9kok kijelolt ellato szervezete.\n\nKIA jarm@\u201d jelent\u00e9se: a KIA altal gyartott KIA g\u00e9pjarmd.\n\n: \u201cHivatalos KIA markakeresked6\u201d jelent\u00e9se: az a ma an- vagy jogi\n> \\ 4 : - i sze-\n: Rey. as ee feljogositott KIA jarmivek Apiary Bye aeare!\noe a Onyvben ismertetett garancidlis feltetelek szerinti javitasok\n\n  \n\nankSZ.Sz\n11600006-0000000'\n\n \n\nKilom\u00e9terora csere adatai\nAjarma kilom\u00e9terdraja oe. -ON,\nMarkaszerviz neve\n\n \n  \n\nkm allasnal K! lett cserelve |\n\n  \n\n\u201cAlkatr\u00e9szek\u201d jelent\u00e9se: :\nKIA alkatre ie : a KIA vagy a MOBIS Altal szallitott eredeti, gyari rene eee\narkaszerviz alairasa\nasznalatbavetel id\u00e9pontja\u201d jelent\u00e9se:\nikalommal atad jelent\u00e9se: az az iddpont, amikor a KIA oie, Pe gg pete at feltiintetett km allast\ndasra kerilt az els6 kiskereskedelmi vasar- Aja nog set\n\n    \n\nev6nek, vagy szolgalati jarmi\nK, jarmGk\u00e9nt hasznalatb\n\u2018be \u2018a ey vagy flottajarmGk\u00e9nt), pare\n\nhasznalatbavetel id\u00e9pontja\u201d meg-"
  },
  {
    "image": "IMG_20241112_134014_anonimized.jpg",
    "caption": "a book is open to a page that says collateral appraisal assistant",
    "ocr": "; atvizsgalas a\nGad Atadas eldtt = coo\neldirasoknak megfeleloen veg\n\nAz atadas eldtti atvizsgalast a KIA\n\nla es :\nJasz, Pla Az i karbantartas-\n\nMark j ki, hogy \u00a2\naD , alah k\u00e9pvisel\nKIAMOTORS siairasat. EZ\nre eee sh hes varbantartasok eV\nccea ls ten le mre ; TT60( +o sara szolgal, ezert k\nKIA markaszerviz'dlairasa @s b\u00e9lyegz\u00e9je pantartasi dokumen\nmegrendeldlapokka\n\u2014_\u2014, egyiitt Srizze Meg, I\nKIA markaszervizne\na teljes dokumenta\nwaceeeenneneneseaeees ; ec jarmG minden tovak\nPe A garancia nem vc\u00a2\n| Km-All&S....eeeeeeesseee ees iene ence ene garancidlis id6szak\n| hibakra, amelyek\ngyartasi hibara, he\naoe hianyossagra vezet\nKe\u00e9rjuk, hogy az id\ntasi intervallumoka\n7 kOnyvben ellendriz\nacne | intervallumok _ tulle\n| lisan megengedet\nBN ) vagy 1 h\u00e9nap.)\n\n \n\n   \n    \n\n  \n\nene Rariarab bekdovetkezik)\n\n \n\nAtadas el\u00e9tti atvizsgalas\n\nbekovetkezik\n(amelyik hamarabb beKoveN"
  },
  {
    "image": "IMG_20241112_134017_anonimized.jpg",
    "caption": "a book with a title of collateral appraisal assistant",
    "ocr": "tuk!\n\nJ\u00e9sz7-Plasztik Aut\u00e9ec entry,\nMarkuk\u00e9pviselet 6 s,..-\nCim: 2151 Fot, Feh\u00e9r.s\n(BP. MB bevezetd N40 coon.\n; Ad\u00e9sz4m: 12939525.,, eon\nok x : om iS\n_, 11600006-00000000-334350-) --------\n\nizldldirasa \u00e9s b\u00e9lyegz\u00e9je\n\n \n\nBe CoS... km\na\nlyik hamarabb bekavetkezik)\n\n \n \n \n    \n   \n    \n \n \n  \n   \n     \n   \n \n\n  \n\n____ 1. id6szakos szerviz\namely v\u00e9grehajtasra keriilt:\n\n \n   \n \n    \n     \n   \n   \n   \n     \n \n\n    \n   \n     \n   \n     \n \n     \n \n    \n\nKmallds:.. 43.322 Mew a oe\n\nJavitasi munkalap SZAMa@? 0.0.0.0. eee\n\nKm-allas:.\n\\\n\n \n\n    \n\nJavitasi munkalap sZAma: ...........cccccceeeeeeee\n\n \n\nTovabba lecser\u00e9l\u00e9sre kerilt: Tovabba lecser\u00e9l\u00e9sre keriilt:\n\nkal @s szamlakkal\n\nValtdolaj ef Valt\u00e9olaj a\n\nk\u00e9r\u00e9sre a hivatalos | Leveg\u00e9sziir\u00e9 Dk | | Levegdsziir\u00e9 x\nek mutassa be. Ezt | Uzemanyagsztir\u00e9 Er | | Uzemanyagsziir\u00e9 \u2014\ncidt at kell adni a Vez\u00e9rmiszij \u2014& | | Vez\u00e9rmiszij a \"Es\npbi tulaidonosanak. | Fekfolyad\u00e9k | | F\u00e9kfolyad\u00e9k 4\nHit\u00e9folyad\u00e9k || Hit\u00e9folyad\u00e9k =\n\n    \n        \n   \n\n  \n\n  \n\n    \n\n \n  \n\nae, aes Szenyiz alamescRermeeedehaz Kit.\nnem anyag- vagy | 92\u00b0 aes Re aaah ha ABRONES Fehervati ut 71-73.\nkarbantartasi PBR co, FeN nen8e?? agpszany: 12083852244\n\n  \n\n9 g02\u00b0\n\\ : t\nA\\ aoe 1) ah\n\n4\n\n       \n \n    \n\n1 sepeyuequey SOH2ZSOPI\n\na Kezel\u00e9si K\u00e9zi-\n\n \n  \n\n  \n\n        \n  \n  \n\nkarbantarta Svetkez6 id\u00e9szakos karbantartas (\u00a9\nZe. (A ntartasi Bvetkezd iddszakos karbantartas A kovet re\nie See IT patum: 2ASL Ok BB Oo\nan eee | | | Datu oe\nGOP ROT Redwcsrn | PT Be\n\nwreeeamen sec ss."
  },
  {
    "image": "IMG_20241112_134025_anonimized.jpg",
    "caption": "a document with a title of collateral appraisal assistant is open",
    "ocr": "Gn Alvazszam: Al yazszam:\n\n    \n \n\n \n    \n    \n   \n   \n     \n     \n    \n    \n  \n\n \n  \n     \n   \n   \n   \n \n\nSRE Sat\n5. idoszakos s Szerviz\n\n    \n \n   \n     \n   \n   \n   \n   \n   \n   \n   \n     \n   \n\n  \n\n4. id\u00e9szakos szerviz\n\n \n   \n  \n   \n \n  \n \n \n \n  \n\n \n \n  \n\n\u2019 a P i TO |\n3. iddszakos Szerv\u2019? 2 ny alt: amely v\u00e9grehajtasra ke i amely vegr\ntasra kerult: amely v\u00e9grehajtasra kerult: 05 C2 | Da <\u2014......:\ngi \u201cO02 ~ z Ze. Q ERT A eecere< ss Datum: .2034...7...0... J J -edd' } patum eT\npattie KA ae Ee Datum ..CAZ& or 6h NAT ciscesst Lh AOU i\n\u00bb \u00a30 Km-allas: Mt DAME eta caine. Km-allas:. 2.4.1 Km-alia@ee\n\nKm-allas:...S@.5%.-4.e52 | Reed bs c\nJavitasi munkalap SZAMA: .....-----e err Javitasi munkalap szama\"' (HCLOSAa Javitasi munkalap szame\n\nJavitasi munkalap SZAMA: \u00ab.-!.-.--sree eee\n\n: o. x x eae Ponta Di \u2018 re k\nTovabba lecser\u00e9l\u00e9sre kerult: Tovabba lecser\u00e9l\u00e9sre kerult: Tovabba lecser\u00e9l\u00e9sre ker Tovabba lecser\u00e9l\u00e9s\n\nValtdolaj Valtoolaj Valtoolaj ol Valtdolaj\n\nee Levegosztir6 0 Leveg\u00e9sztir6 v Oh Leveg\u00e9szUr6\nUzemanyagszir6 Uzemanyagsziir\u00e9 | | Uzemanyagsziir\u00e9 = Uzemanyagsztr6\nee Vez\u00e9rmiiszij | | Vez\u00e9ermiszij a Vez\u00e9rmiszij\nFekfolyadek F\u00e9kfolyad\u00e9k \u2014\u2014+| | F\u00e9kfolyad\u00e9k \u00a3 F\u00e9kfolyad\u00e9k\noe Hiit\u00e9folyad\u00e9k | | Hit\u00e9folyad\u00e9k & Hit\u00e9folyad\u00e9k\n\n   \n  \n \n\n        \n \n\n=a.\n\u201ceee Sata wet\n\n4119 Bp., Feh\u00e9rvari ut 71-73.\n\n9sz4m: 12062852.2-44\n\nSzerviz alairasa \u00e9s b\u00e9lyegzdje:\nABRONCS Kereskedohar | or\n4044 Bdapest\n\nSzerviz alairasa es:belye:\n\ngon F\u00e9skedchiz Kft,\n1y19 a task enya it 24-73,\neee -2-44\n\noe\n\n NMBSVUE\nYS YER Bip, Geernisnr\n\n    \n      \n\nES?) FS\n\nS\nA k\u00e9vetkezo id\u00e9szakos karbantarta\n\nesed\u00e9kesseg\u00ae\n\nDatum:. 1922. ae OP\n\nKm-allas:...4/ QB. Ad: {\n(amelyiket eldbb ele\"!\n\n   \n  \n    \n\nIid\u00e9szakos karbantartas igazolasa\n\n \n\n17-GKIA-ALL_-207-093"
  },
  {
    "image": "IMG_20241112_134028_anonimized.jpg",
    "caption": "a book with a title of collateral appraisal assistant is open",
    "ocr": "i 7. id\u00e9szakos Szerviz\n\ni iv . dds yi\namely v\u00e9grehajtasra keriilt: _laGszakos szerviz 7\n\n \n\n  \n    \n \n \n \n    \n  \n   \n  \n\nROSA RCRANRGANAANITAV IAS OD LAE\n\namely V\u00e9grehaitasra keriilt\n\n   \n  \n \n\nGaUeTeseHisistereditesss HAI Ady, ) Datum\n\nKm-allas:...\n\nJavitasi munkalap sz4ma\n\n\u00e9 \u2018s Tovabba | \u00e9l\u00e9 tilt:\nl\u00e9sre keriilt: ecser\u00e9l\u00e9sre keriilt:\n\nTovabba lecser\u00e9l\u00e9sre keriilt:\nValtdolaj\n\n        \n \n   \n   \n \n \n  \n\nazolasa\n\nOo Valt\u00e9olaj\nLeveg\u00e9sziir\u00e9 O || Leveg\u00e9sztir\u00e9 =\nUzemanyagsziir6 Oo Uzemanyagsztir6\nVez\u00e9rmiszij Oo Vez\u00e9rmiszij\nF\u00e9kfolyad\u00e9k O || F\u00e9kfolyadek\nHitd\u00e9folyad\u00e9k Oo Hiit\u00e9folyad\u00e9k\n\n   \n \n\n  \n\nSzerviz alairasa \u00e9s belyegzoje\n1s. b\u00e9lyegzdje: .\n\nske Shaz Kft.\nehenyari uty .\n\nSzerviz alairasa \u00e9s b\u00e9lyegzdje:\n\ni\n\n     \n\n   \n     \n\n    \n\n   \n\n  \n\n \n\n, 3s 6 id\u00e9szakos karbantartas\n\u2014_\u2014\u2014\u2014 ; A k\u00e9vetkez6 idoszakos\n\nos karbantartas esed\u00e9kess\u00e9ge\nd\u00e9kessege\n\nid\u00e9szakos karbantartas ig\n\n.\npepepeeeprpessere\n\naes aia\nsans \u2014.\neen a i -"
  }
]